aleatorik_pycommon-1.54.0.dist-info/licenses/LICENSE
pylogger/__init__.py
pylogger/config.py
pylogger/logger.py
pylogger/logging_client.py
pylogger/middleware.py
pylogger/model.py
pylogger/utils/__init__.py
pylogger/utils/helper.py
pylogger/utils/template.py
aleatorik_pycommon-1.54.0.dist-info/METADATA
aleatorik_pycommon-1.54.0.dist-info/WHEEL
aleatorik_pycommon-1.54.0.dist-info/top_level.txt
aleatorik_pycommon-1.54.0.dist-info/RECORD
