Metadata-Version: 2.4
Name: aleatorik-pycommon
Version: 1.54.0
Summary: Aleatorik PyCommon - 구조화된 로깅 및 공통 유틸리티 라이브러리
Author-email: Aleatorik <info@aleatorik.com>
License: MIT
Keywords: logging,utilities,aleatorik,fastapi,structured-logging
Classifier: Programming Language :: Python :: 3.12
Classifier: License :: OSI Approved :: MIT License
Requires-Python: <4,>=3.11
License-File: LICENSE
Requires-Dist: loguru<0.8.0,>=0.7.3
Requires-Dist: pydantic-settings<3.0.0,>=2.7.1
Requires-Dist: requests<3.0.0,>=2.32.3
Provides-Extra: dev
Requires-Dist: pytest>=8.3.2; extra == "dev"
Requires-Dist: ruff>=0.1.0; extra == "dev"
Requires-Dist: pre-commit>=3.0.0; extra == "dev"
Dynamic: license-file
